napari_data_preview/__init__.py
napari_data_preview/_dock_widget.py
napari_data_preview/_reader.py
napari_data_preview/_version.py
napari_data_preview/napari.yaml
napari_data_preview-0.0.3a0.dist-info/LICENSE
napari_data_preview-0.0.3a0.dist-info/METADATA
napari_data_preview-0.0.3a0.dist-info/WHEEL
napari_data_preview-0.0.3a0.dist-info/entry_points.txt
napari_data_preview-0.0.3a0.dist-info/top_level.txt
napari_data_preview-0.0.3a0.dist-info/RECORD
